previsedx_esopredict_pdf_file_utils/__init__.py
previsedx_esopredict_pdf_file_utils/console_helper.py
previsedx_esopredict_pdf_file_utils/constants.py
previsedx_esopredict_pdf_file_utils/file_utils.py
previsedx_esopredict_pdf_file_utils/system_caller.py
previsedx_esopredict_pdf_file_utils/writer.py
previsedx_esopredict_pdf_file_utils/conf/config.yaml
previsedx_esopredict_pdf_file_utils-0.1.0.dist-info/AUTHORS.rst
previsedx_esopredict_pdf_file_utils-0.1.0.dist-info/LICENSE
previsedx_esopredict_pdf_file_utils-0.1.0.dist-info/METADATA
previsedx_esopredict_pdf_file_utils-0.1.0.dist-info/WHEEL
previsedx_esopredict_pdf_file_utils-0.1.0.dist-info/top_level.txt
previsedx_esopredict_pdf_file_utils-0.1.0.dist-info/RECORD
